Metadata-Version: 2.4
Name: iflow-mcp_needle-mcp
Version: 1.0.0
Summary: Needle MCP integration
Author-email: Onur Eken <onur@needle.app>, Jan Heimes <jan@needle.app>
License-Expression: MIT
License-File: LICENSE
Requires-Dist: mcp>=1.1.0
Requires-Dist: needle-python>=0.6.0
Requires-Dist: python-dotenv>=1.0.1
